PBCT/__init__.py
PBCT/classes.py
PBCT/experimental_classes.py
PBCT/split_data.py
PBCT/train_test.py
PBCT/visualize.py
pbct-0.3.2.data/scripts/PBCT
pbct-0.3.2.dist-info/LICENSE
pbct-0.3.2.dist-info/METADATA
pbct-0.3.2.dist-info/WHEEL
pbct-0.3.2.dist-info/top_level.txt
pbct-0.3.2.dist-info/RECORD
