Metadata-Version: 2.1
Name: pbct
Version: 0.3.2
Summary: Predictive Bi-Clustering Trees in Python.
Home-page: http://github.com/pedroilidio/PCT
Author: Pedro Ilidio
Author-email: pedrilidio@gmail.com
License: GPLv3
Platform: UNKNOWN
License-File: LICENSE
Requires-Dist: pandas
Requires-Dist: numpy (<=1.21)
Requires-Dist: numba
Requires-Dist: tqdm
Provides-Extra: tree_visualization
Requires-Dist: graphviz ; extra == 'tree_visualization'
Requires-Dist: matplotlib ; extra == 'tree_visualization'
